{"rating": "1: Reject", "experience_assessment": "I have read many papers in this area.", "review_assessment:_checking_correctness_of_derivations_and_theory": "I assessed the sensibility of the derivations and theory.", "review_assessment:_checking_correctness_of_experiments": "I did not assess the experiments.", "title": "Official Blind Review #1", "review_assessment:_thoroughness_in_paper_reading": "I made a quick assessment of this paper.", "review": "Text normalization or the transformation of words from the written to the spoken form is an important and realistic question in natural language processing. This paper aims to use sequence-to-sequence models to perform text normalization.\n\nHowever, this paper does not use the official template and the content is too short to be a conference paper.\nI suggested resubmitting to another (NLP) conference after extending the content with detailed description for the model and the method, and conducting more experiments on public acceptable benchmarks.  "}